Workbook

Sheet Read Me
A1: Kerala private clinical establishments — postcard mail list
A3: Source | B3: Register of Clinical Establishments, Kerala State Council for Clinical Establishments (KSCCE), as on 01.08.2026
A4: Source files | B4: Clinical_Permanent_AUG2026 and Clinical_Provisional_AUG2026 (both downloaded from clinicalestablishments.kerala.gov.in)
A5: Built | B5: 20 September 2026
A7: What was done
A8: 1 | B8: Both registers combined: 19,134 rows.
A9: 2 | B9: Filtered to OWNERSHIP = PVT. This removes 6,393 government establishments (PHCs, CHCs, family health centres, district hospitals) which are not buyers.
A10: 3 | B10: The register jams clinic name, address, landline, mobile and email into a single cell. These were parsed into separate columns.
A11: 4 | B11: Duplicates removed where the same name appears at the same address in both registers (435 rows). Branches of the same chain at different addresses were KEPT — each is its own reception desk.
A12: 5 | B12: PIN codes recovered. Only 10% of rows carried one. Post-office and place names in each address were matched against the India Post directory, restricted to the establishment's own district. Coverage is now 65%.
A14: How to use it
B15: Go to the "Mail List" tab. Use the filter arrows on row 1.
B16: Filter District to your own district first. Filter Category to drop what you do not want — Laboratory, Diagnostic Imaging Centre and Multi Specialty Hospital are probably not your buyers; Health Centre/Clinics/Polyclinics, Dental and Day Care Centre are.
B17: Sort by PIN Confidence and post the High rows first.
B18: The "Address Block" column is ready to print as-is — it is already laid out as the lines of a postal address.
A20: PIN Confidence
A21: High | B21: The PIN was printed in the clinic's own registered address, or matched an explicit "<place> P.O" in it. Post these first.
A22: Medium | B22: No PIN given, but exactly one place name in the address matches a post office in that district. Reliable, but not the clinic's own wording.
A23: Low | B23: Several place names matched different post offices. The PIN shown is a guess. The card will usually still arrive on the district and place name — consider deleting the PIN rather than printing a wrong one.
A24: No PIN | B24: No match found. Still postable if the address names a place and a post office; India Post will sort it by hand, more slowly.
A26: Caveat | B26: The Act exempts establishments "offering only consultation services", so a doctor with nothing but a consulting room may not appear here at all.
A27: Caveat | B27: 112 rows carry a PIN that the India Post directory assigns to a neighbouring district. These came from the clinic's own address and were left as written — border post offices are classified inconsistently between the two sources.
A28: Caveat | B28: 19 rows have no usable street address at all — only a clinic name. They are marked Postable = No. Their phone and email still work.
A29: Note | B29: Every row also has a mobile number and an email address, both at 100% coverage. See the Mobile and Email columns.

Sheet Mail List
A1: Clinic Name | B1: Address | C1: District | D1: PIN | E1: PIN Confidence | F1: Address Block | G1: Category | H1: System of Medicine | I1: Registration | J1: Reg No | K1: Mobile | L1: Landline | M1: Email | N1: Postable
A2: Anaril Vaidyasala | B2: Anaril Vaidyasala , Thrikunnapuzha, 9 | C2: Alappuzha | E2: No PIN | F2: Anaril Vaidyasala Anaril Vaidyasala, Thrikunnapuzha, 9 Kerala, Alappuzha | G2: Any Other | H2: Ayurveda | I2: Provisional | J2: T32554AY6983, Period - 19-02-2024 To 18-08-2028 | K2: 9446918019 | M2: anarilvaidyasala@gmail.com | N2: Yes
A3: DISEASE HELPLINE CENTRE | B3: DISEASE HELPLINE CENTRE, AVALUKKUNNU.P.O, POONTHOPPU WARD, ALAPPUZHA, 688006 | C3: Alappuzha | D3: 688006 | E3: High | F3: DISEASE HELPLINE CENTRE DISEASE HELPLINE CENTRE, AVALUKKUNNU.P.O, POONTHOPPU WARD Kerala, Alappuzha - 688006 | G3: Any Other | H3: Modern Medicine | I3: Provisional | J3: T32554MM5499, Period - 06-02-2024 To 05-08-2028 | K3: 9447212439 | L3: 04772232039 | M3: drshaji.alpy@gmail.com | N3: Yes
A4: Incare Medical Centre and Research Institute | B4: Murugan Junction, Karukayil Ward, Avalookunnu P.O, Kalarikal | C4: Alappuzha | D4: 688006 | E4: High | F4: Incare Medical Centre and Research Institute Murugan Junction, Karukayil Ward, Avalookunnu P.O, Kalarikal Kerala, Alappuzha - 688006 | G4: Any Other | H4: Yoga and Naturopathy | I4: Provisional | J4: T32554YN0777, Period - 19-07-2023 To 18-07-2027 | K4: 9744491144 | L4: 08921883156 | M4: incaregroups@gmail.com | N4: Yes
A5: KIOT ORTHO AND FAMILY CLINIC | B5: Ground Floor, Thiruvonam Complex, Near Puthuvilapadi Jun, Oripuram, Chennithala P O, Mavelikara, Kerala | C5: Alappuzha | D5: 690105 | E5: High | F5: KIOT ORTHO AND FAMILY CLINIC Ground Floor, Thiruvonam Complex, Near Puthuvilapadi Jun, Oripuram, Chennithala P O, Mavelikara Kerala, Alappuzha - 690105 | G5: Any Other | H5: Modern Medicine | I5: Provisional | J5: T32554MM2909, Period - 23-01-2024 To 22-07-2028 | K5: 9395241066 | L5: 04792322368 | M5: mzontalh@gmail.com | N5: Yes
A6: MATHERY MEDICAL MISSION HOSPITAL THOTTAPPALLY | B6: MATHERY MEDICAL MISSION HOSPITAL , THOTTAPPALLY P.O ALAPPUZHA | C6: Alappuzha | D6: 688001 | E6: Medium | F6: MATHERY MEDICAL MISSION HOSPITAL THOTTAPPALLY MATHERY MEDICAL MISSION HOSPITAL, THOTTAPPALLY P.O Kerala, Alappuzha - 688001 | G6: Any Other | H6: Modern Medicine | I6: Provisional | J6: T32554MM4353, Period - 29-01-2024 To 28-07-2028 | K6: 9645806225 | L6: 04772296225 | M6: matherydrislah@gmail.com | N6: Yes
A7: P K M Clinic | B7: P K M Clinic , Valanjavazhi , Vandanam P O | C7: Alappuzha | E7: No PIN | F7: P K M Clinic P K M Clinic, Valanjavazhi, Vandanam P O Kerala, Alappuzha | G7: Any Other | H7: Modern Medicine | I7: Provisional | J7: T32554MM487, Period - 23-05-2023 To 22-11-2027 | K7: 9495162779 | L7: 04792413014 | M7: radhakrishnank9495@gmail.com | N7: Yes
A8: SMM HOSPITAL | B8: SMM HOSPITAL, NANGIARKULANGARA P.O, ALAPPUZHA | C8: Alappuzha | D8: 690513 | E8: High | F8: SMM HOSPITAL SMM HOSPITAL, NANGIARKULANGARA P.O Kerala, Alappuzha - 690513 | G8: Any Other | H8: Modern Medicine | I8: Provisional | J8: T32554MM4227, Period - 29-01-2024 To 28-07-2028 | K8: 9447040640 | L8: 04792412640 | M8: ksgopal12345@gmail.com | N8: Yes
A9: THE AROOR CLINIC | B9: Ground Floor AP 20 160a Kannikkatt Building Near St Augustine Church Aroor Bypass Aroor Alappuzha | C9: Alappuzha | D9: 688001 | E9: Low | F9: THE AROOR CLINIC Ground Floor AP 20 160a Kannikkatt Building Near St Augustine Church Aroor Bypass Aroor Kerala, Alappuzha - 688001 | G9: Any Other | H9: Modern Medicine | I9: Provisional | J9: T32554MM5583, Period - 06-02-2024 To 05-08-2028 | K9: 9895052501 | L9: 04782990224 | M9: thearoorclinic2022@gmail.com | N9: Yes
A10: AB SCANS & LABORATORY | B10: NEAR GOVT HOSPITAL, KAYAMKULAM | C10: Alappuzha | D10: 690502 | E10: Medium | F10: AB SCANS & LABORATORY NEAR GOVT HOSPITAL, KAYAMKULAM Kerala, Alappuzha - 690502 | G10: Both Laboratory and Diagnostic Imaging Centre | H10: Modern Medicine | I10: Provisional | J10: T32554MMBOTH00013, Period - 07-03-2020 To 06-09-2024 | K10: 9207037777 | L10: 04792445149 | M10: abscanskylm@gmail.com | N10: Yes
A11: ABHIRAMI LABORATORY | B11: Abhirami Laboratory, Muttel Jn., Kuttamperoor P.O, Mannar | C11: Alappuzha | D11: 689623 | E11: High | F11: ABHIRAMI LABORATORY Abhirami Laboratory, Muttel Jn., Kuttamperoor P.O, Mannar Kerala, Alappuzha - 689623 | G11: Both Laboratory and Diagnostic Imaging Centre | H11: Modern Medicine | I11: Provisional | J11: T32554MMBOTH00008, Period - 28-11-2019 To 27-05-2024 | K11: 9605617687 | M11: sreedhanya528@gmail.com | N11: Yes
A12: ASWINI CLINICAL LABORATORY | B12: VALIYAPARAMBIL OPPOSITE GOVT HOSPITAL MANNAR | C12: Alappuzha | E12: No PIN | F12: ASWINI CLINICAL LABORATORY VALIYAPARAMBIL OPPOSITE GOVT HOSPITAL MANNAR Kerala, Alappuzha | G12: Both Laboratory and Diagnostic Imaging Centre | H12: Modern Medicine | I12: Provisional | J12: T32554MMBOTH00004, Period - 02-10-2019 To 01-04-2024 | K12: 9746280148 | L12: 04792312712 | M12: reshmi.krshnn@gmail.com | N12: Yes
A13: AV DIAGNOSTIC CENTRE | B13: 301 , NEAR SB AUDITORIUM , VAZHIYAMPALAM , KARUVATTA PO , HARIPPAD | C13: Alappuzha | E13: No PIN | F13: AV DIAGNOSTIC CENTRE 301, NEAR SB AUDITORIUM, VAZHIYAMPALAM, KARUVATTA PO, HARIPPAD Kerala, Alappuzha | G13: Both Laboratory and Diagnostic Imaging Centre | H13: Modern Medicine | I13: Provisional | J13: T32554MM3031, Period - 24-01-2024 To 23-07-2028 | K13: 8139810493 | L13: 04792995393 | M13: avdcrec@gmail.com | N13: Yes
A14: BIOTECH LAB & SCANS | B14: SV MALL, NEAR PUTHIYIDOM TEMPLE, KAYAMKULAM | C14: Alappuzha | D14: 690502 | E14: Medium | F14: BIOTECH LAB & SCANS SV MALL, NEAR PUTHIYIDOM TEMPLE, KAYAMKULAM Kerala, Alappuzha - 690502 | G14: Both Laboratory and Diagnostic Imaging Centre | H14: Modern Medicine | I14: Provisional | J14: T32554MMBOTH00007, Period - 26-11-2019 To 25-05-2024 | K14: 7025341122 | M14: biotechlabkylm@gmail.com | N14: Yes
A15: BIOVISION INDIA SPECIALITY DIAGNOSTIC CENTRE | B15: AISWARYA PLAZA, GOVT. HOSPITAL JN., THAZHAKARA, MAVELIKARA | C15: Alappuzha | D15: 690102 | E15: Medium | F15: BIOVISION INDIA SPECIALITY DIAGNOSTIC CENTRE AISWARYA PLAZA, GOVT. HOSPITAL JN., THAZHAKARA, MAVELIKARA Kerala, Alappuzha - 690102 | G15: Both Laboratory and Diagnostic Imaging Centre | H15: Modern Medicine | I15: Permanent | J15: P32554MM2970, Period - 15-02-2025 To 14-02-2030 | K15: 9446300734 | L15: 04792340082 | M15: biovisionkra@gmail.com | N15: Yes
A16: Biovision India Speciality Diagnostic Centre | B16: KARUVELIL BUILDING, NEAR SOUTH INDIAN BANK, MANNAR | C16: Alappuzha | E16: No PIN | F16: Biovision India Speciality Diagnostic Centre KARUVELIL BUILDING, NEAR SOUTH INDIAN BANK, MANNAR Kerala, Alappuzha | G16: Both Laboratory and Diagnostic Imaging Centre | H16: Modern Medicine | I16: Provisional | J16: T32554MMBOTH00006, Period - 02-10-2019 To 01-04-2024 | K16: 9447360734 | M16: biovisionkra@gmail.com | N16: Yes
A17: CHETHANA JANAKEEYA LAB | B17: CHETHANA JANAKEEYA LAB , TDMC P.O , VANDANAM , ALAPPUZHA | C17: Alappuzha | D17: 688001 | E17: Medium | F17: CHETHANA JANAKEEYA LAB CHETHANA JANAKEEYA LAB, TDMC P.O, VANDANAM Kerala, Alappuzha - 688001 | G17: Both Laboratory and Diagnostic Imaging Centre | H17: Modern Medicine | I17: Provisional | J17: T32554MM933, Period - 06-09-2023 To 05-03-2028 | K17: 8593082277 | L17: 04772282277 | M17: chetanapalliative@gmail.com | N17: Yes
A18: CITY LABORATORY | B18: Y.M.C.A Building, Near Govt.Hospital, Chengannur | C18: Alappuzha | D18: 689121 | E18: Medium | F18: CITY LABORATORY Y.M.C.A Building, Near Govt.Hospital, Chengannur Kerala, Alappuzha - 689121 | G18: Both Laboratory and Diagnostic Imaging Centre | H18: Modern Medicine | I18: Provisional | J18: T32554MMBOTH00016, Period - 28-05-2020 To 27-11-2024 | K18: 9388599996 | M18: citylabcgn@gmail.com | N18: Yes
A19: Chacko Memorial Diagnostics | B19: Chacko Memorial Diagnostics, Near Govt. Hospital, Thazhakara | C19: Alappuzha | D19: 690102 | E19: Medium | F19: Chacko Memorial Diagnostics Chacko Memorial Diagnostics, Near Govt. Hospital, Thazhakara Kerala, Alappuzha - 690102 | G19: Both Laboratory and Diagnostic Imaging Centre | H19: Modern Medicine | I19: Provisional | J19: T32554MMBOTH00001, Period - 25-07-2019 To 24-01-2024 | K19: 9447006316 | L19: 04792303222 | M19: chackomemorial@gmail.com | N19: Yes
A20: DDRC AGILUS PATH LABS | B20: DDRC AGILUS PATHLABS , NEAR ALAPPUZHA GH , PALACE WARD | C20: Alappuzha | D20: 688001 | E20: Medium | F20: DDRC AGILUS PATH LABS DDRC AGILUS PATHLABS, NEAR ALAPPUZHA GH, PALACE WARD Kerala, Alappuzha - 688001 | G20: Both Laboratory and Diagnostic Imaging Centre | H20: Modern Medicine | I20: Permanent | J20: P32554MM4896, Period - 03-09-2025 To 03-09-2030 | K20: 9446508300 | L20: 09446508300 | M20: sheela.benny@agilus.in | N20: Yes
A21: DDRC AGILUS PATHLABS LIMITED | B21: DDRC AGILUS PATHLABS LIMITED, GROUND FLOOR NEAR IRON BRIDGE, CHERTHALA | C21: Alappuzha | D21: 688524 | E21: Medium | F21: DDRC AGILUS PATHLABS LIMITED DDRC AGILUS PATHLABS LIMITED, GROUND FLOOR NEAR IRON BRIDGE, CHERTHALA Kerala, Alappuzha - 688524 | G21: Both Laboratory and Diagnostic Imaging Centre | H21: Modern Medicine | I21: Permanent | J21: P32554MM0686, Period - 15-05-2024 To 14-05-2029 | K21: 6282016827 | L21: 06282016827 | M21: cherthalaironbridge.ddrc@agilus.in | N21: Yes
A22: DDRC AGILUS PATHLABS LIMITED CHERTHALA | B22: DDRC AGILUS PATHLABS LIMITED GROUND FLOOROPP SNMM GOVT HSS CHERTHALA | C22: Alappuzha | D22: 688524 | E22: Medium | F22: DDRC AGILUS PATHLABS LIMITED CHERTHALA DDRC AGILUS PATHLABS LIMITED GROUND FLOOROPP SNMM GOVT HSS CHERTHALA Kerala, Alappuzha - 688524 | G22: Both Laboratory and Diagnostic Imaging Centre | H22: Modern Medicine | I22: Permanent | J22: P32554MM0754, Period - 24-05-2024 To 23-05-2029 | K22: 9074558956 | L22: 09074558956 | M22: cherthala.ddrc@agilus.in | N22: Yes
A23: Dial Scan Doctors Imageology and Laboratory | B23: Vandanam, Alappuzha | C23: Alappuzha | D23: 688001 | E23: Medium | F23: Dial Scan Doctors Imageology and Laboratory Vandanam Kerala, Alappuzha - 688001 | G23: Both Laboratory and Diagnostic Imaging Centre | H23: Modern Medicine | I23: Provisional | J23: T32554MM13099, Period - 27-01-2025 To 26-07-2029 | K23: 9744169000 | L23: 04772280022 | M23: ashaloui@gmail.com | N23: Yes
A24: Doctors Imageology and Laboratory | B24: 263G, Alappuzha | C24: Alappuzha | D24: 688001 | E24: Medium | F24: Doctors Imageology and Laboratory 263G Kerala, Alappuzha - 688001 | G24: Both Laboratory and Diagnostic Imaging Centre | H24: Modern Medicine | I24: Provisional | J24: T32554MM13097, Period - 27-01-2025 To 26-07-2029 | K24: 9744169000 | L24: 04772280022 | M24: ashaloui@gmail.com | N24: Yes
A25: HI TECHDIAGNOSTIC CENTRE | B25: PARAVOOR JUNCTION , PATTOLIMARKET PO , KANDALLOOR NORTH | C25: Alappuzha | D25: 690531 | E25: High | F25: HI TECHDIAGNOSTIC CENTRE PARAVOOR JUNCTION, PATTOLIMARKET PO, KANDALLOOR NORTH Kerala, Alappuzha - 690531 | G25: Both Laboratory and Diagnostic Imaging Centre | H25: Modern Medicine | I25: Provisional | J25: T32554MM1601, Period - 22-12-2023 To 21-06-2028 | K25: 9946410677 | L25: 09946410677 | M25: hitechdiagnosticcentre77@gmail.com | N25: Yes
A26: HITECH LAB & ECG DIAGNOSTIC CENTRE | B26: NEAR MARARIKULAM TEMPLE, SL PURAM P O, ALAPPUZHA | C26: Alappuzha | D26: 688001 | E26: Medium | F26: HITECH LAB & ECG DIAGNOSTIC CENTRE NEAR MARARIKULAM TEMPLE, SL PURAM P O Kerala, Alappuzha - 688001 | G26: Both Laboratory and Diagnostic Imaging Centre | H26: Modern Medicine | I26: Provisional | J26: T32554MMBOTH00017, Period - 09-11-2020 To 08-05-2025 | K26: 9526768089 | L26: 04772249231 | M26: hitechlabmkm@gmail.com | N26: Yes
A27: K R MEDICAL CLINIC PRIVATE LIMITED | B27: East Of St Mary s Bridge Cherthala | C27: Alappuzha | D27: 688524 | E27: Medium | F27: K R MEDICAL CLINIC PRIVATE LIMITED East Of St Mary s Bridge Cherthala Kerala, Alappuzha - 688524 | G27: Both Laboratory and Diagnostic Imaging Centre | H27: Modern Medicine | I27: Permanent | J27: P32554MM5816, Period - 21-01-2026 To 21-01-2031 | K27: 9020918833 | L27: 09020918833 | M27: krlabcherthala@gmail.com | N27: Yes
A28: KAYAMKULAM SCANS | B28: GLASS TOWER , CHIRAKADAVAM , KAYAMKULAM | C28: Alappuzha | D28: 690502 | E28: Medium | F28: KAYAMKULAM SCANS GLASS TOWER, CHIRAKADAVAM, KAYAMKULAM Kerala, Alappuzha - 690502 | G28: Both Laboratory and Diagnostic Imaging Centre | H28: Modern Medicine | I28: Provisional | J28: T32554MM1925, Period - 29-12-2023 To 28-06-2028 | K28: 9447789580 | L28: 09447789580 | M28: kayamkulamscans@gmail.com | N28: Yes
A29: KERALA PATHOLOGICAL LABORATORY | B29: KAILAS BUILDING , HARIPPAD | C29: Alappuzha | E29: No PIN | F29: KERALA PATHOLOGICAL LABORATORY KAILAS BUILDING, HARIPPAD Kerala, Alappuzha | G29: Both Laboratory and Diagnostic Imaging Centre | H29: Modern Medicine | I29: Provisional | J29: T32554MM4235, Period - 29-01-2024 To 28-07-2028 | K29: 9447749179 | L29: 09447749179 | M29: keralapathlab@yahoo.co.in | N29: Yes
A30: KOCHIN CLINICAL LABORATORY AND X-RAY | B30: KOCHIN CLINICAL LAB, RAIBAN COMPLEX, ALAPPUZHA | C30: Alappuzha | D30: 688001 | E30: Medium | F30: KOCHIN CLINICAL LABORATORY AND X-RAY KOCHIN CLINICAL LAB, RAIBAN COMPLEX Kerala, Alappuzha - 688001 | G30: Both Laboratory and Diagnostic Imaging Centre | H30: Modern Medicine | I30: Provisional | J30: T32554MMBOTH00012, Period - 14-02-2020 To 13-08-2024 | K30: 9946046364 | M30: akhilsatheesh86@gmail.com | N30: Yes
A31: KRISHNA DIAGNOSTIC CENTRE | B31: KRISHNA DIAGNOSTIC CENTRE OPP TALUK HOSPITAL THURAVOOR | C31: Alappuzha | D31: 688532 | E31: Medium | F31: KRISHNA DIAGNOSTIC CENTRE KRISHNA DIAGNOSTIC CENTRE OPP TALUK HOSPITAL THURAVOOR Kerala, Alappuzha - 688532 | G31: Both Laboratory and Diagnostic Imaging Centre | H31: Modern Medicine | I31: Provisional | J31: T32554MMBOTH00009, Period - 10-12-2019 To 09-06-2024 | K31: 9249740460 | L31: 04782561479 | M31: krishnalab70@gmail.com | N31: Yes
A32: MDRC SCANS AND HEALTHCARE PVT LTD | B32: OPP EMS STADIUM BEACH ROAD ALAPPUZHA | C32: Alappuzha | D32: 688001 | E32: Medium | F32: MDRC SCANS AND HEALTHCARE PVT LTD OPP EMS STADIUM BEACH ROAD Kerala, Alappuzha - 688001 | G32: Both Laboratory and Diagnostic Imaging Centre | H32: Modern Medicine | I32: Provisional | J32: T32554MM2097, Period - 01-01-2024 To 30-06-2028 | K32: 8547337460 | L32: 04772237461 | M32: mdrc.alpy@gmail.com | N32: Yes
A33: MEDIVISION SCAN AND DIAGNOSTIC RESEARCH CENTRE | B33: MEDIVISION SCAN AND DIAGNOSTIC RESERCH CENTRE PVT.LTD, NEAR GOVERNMENT HOSPITAL. MAVELIKARA | C33: Alappuzha | E33: No PIN | F33: MEDIVISION SCAN AND DIAGNOSTIC RESEARCH CENTRE MEDIVISION SCAN AND DIAGNOSTIC RESERCH CENTRE PVT.LTD, NEAR GOVERNMENT HOSPITAL. MAVELIKARA Kerala, Alappuzha | G33: Both Laboratory and Diagnostic Imaging Centre | H33: Modern Medicine | I33: Provisional | J33: T32554MM2213, Period - 05-01-2024 To 04-07-2028 | K33: 8547089595 | L33: 08547089595 | M33: medivision9595@gmail.com | N33: Yes
A34: METROPOLIS HEALTHCARE LIMITED | B34: SANKARS LAB METROPOLIS , OPPOSITE EXCISE OFFICE , NEAR GENERAL HOSPITAL, ALAPPUZHA | C34: Alappuzha | D34: 688001 | E34: Medium | F34: METROPOLIS HEALTHCARE LIMITED SANKARS LAB METROPOLIS, OPPOSITE EXCISE OFFICE, NEAR GENERAL HOSPITAL Kerala, Alappuzha - 688001 | G34: Both Laboratory and Diagnostic Imaging Centre | H34: Modern Medicine | I34: Provisional | J34: T32554MM1107, Period - 19-10-2023 To 18-04-2028 | K34: 9947711185 | L34: 04772260019 | M34: jyothilakshmi.r@metropolisindia.com | N34: Yes
A35: MIDAS SCANS & LABORATORY | B35: NIZA CENTER, GROUND FLOOR, GENERAL HOSPITAL JUNCTION, NEAR SBI, BEACH ROAD, ALAPPUZHA | C35: Alappuzha | D35: 688001 | E35: Medium | F35: MIDAS SCANS & LABORATORY NIZA CENTER, GROUND FLOOR, GENERAL HOSPITAL JUNCTION, NEAR SBI, BEACH ROAD Kerala, Alappuzha - 688001 | G35: Both Laboratory and Diagnostic Imaging Centre | H35: Modern Medicine | I35: Provisional | J35: T32554MMBOTH00010, Period - 10-12-2019 To 09-06-2024 | K35: 9447734412 | L35: 04772251952 | M35: midasscans@gmail.com | N35: Yes
A36: Medivision Scan and Diagnostic Research Centre | B36: Puthiyidom, Kayamkulam, Kerala 690502 | C36: Alappuzha | D36: 690502 | E36: High | F36: Medivision Scan and Diagnostic Research Centre Puthiyidom, Kayamkulam Kerala, Alappuzha - 690502 | G36: Both Laboratory and Diagnostic Imaging Centre | H36: Modern Medicine | I36: Provisional | J36: T32554MM4145, Period - 29-01-2024 To 28-07-2028 | K36: 8547189595 | L36: 08547189595 | M36: medkylm@gmail.com | N36: Yes
A37: Microlab Scan And Diagnostics | B37: Sree Muruga Complex, Near Thazakkara MarThoma Church | C37: Alappuzha | E37: No PIN | F37: Microlab Scan And Diagnostics Sree Muruga Complex, Near Thazakkara MarThoma Church Kerala, Alappuzha | G37: Both Laboratory and Diagnostic Imaging Centre | H37: Modern Medicine | I37: Permanent | J37: P32554MM1214, Period - 16-09-2024 To 15-09-2029 | K37: 9526417700 | L37: 00000000000 | M37: microlabmavelikkara@gmail.com | N37: Yes
A38: Microlab laboratories | B38: Vaidyan parampil buliding , Charummoodu , Chunakkara , Alappuzha | C38: Alappuzha | D38: 688001 | E38: Medium | F38: Microlab laboratories Vaidyan parampil buliding, Charummoodu, Chunakkara Kerala, Alappuzha - 688001 | G38: Both Laboratory and Diagnostic Imaging Centre | H38: Modern Medicine | I38: Permanent | J38: P32554MM2486, Period - 28-01-2025 To 27-01-2030 | K38: 8075374539 | L38: 09539359777 | M38: microlabcharummoodu@gmail.com | N38: Yes
A39: NEW DESINGANAD SCANS | B39: PUTHIYOIDOM, OPP.TRIVENI SUPER MARKET, KAYAMKULAM | C39: Alappuzha | D39: 690502 | E39: Medium | F39: NEW DESINGANAD SCANS PUTHIYOIDOM, OPP.TRIVENI SUPER MARKET, KAYAMKULAM Kerala, Alappuzha - 690502 | G39: Both Laboratory and Diagnostic Imaging Centre | H39: Modern Medicine | I39: Provisional | J39: T32554MMBOTH00014, Period - 07-03-2020 To 06-09-2024 | K39: 9496257747 | M39: newdesinganad@gmail.com | N39: Yes
A40: NEW DESINGANAD SCANS | B40: oppo.thriveni supermarket , gazel arcade , charumood po | C40: Alappuzha | E40: No PIN | F40: NEW DESINGANAD SCANS oppo.thriveni supermarket, gazel arcade, charumood po Kerala, Alappuzha | G40: Both Laboratory and Diagnostic Imaging Centre | H40: Modern Medicine | I40: Provisional | J40: T32554MM89, Period - 31-01-2023 To 30-07-2027 | K40: 9496257747 | L40: 04792444411 | M40: newdesinganad@gmail.com | N40: Yes
A41: NEW HITECH DIAGNOSTIC CENTRE | B41: 1 472 A AROOR | C41: Alappuzha | D41: 688534 | E41: Medium | F41: NEW HITECH DIAGNOSTIC CENTRE 1 472 A AROOR Kerala, Alappuzha - 688534 | G41: Both Laboratory and Diagnostic Imaging Centre | H41: Modern Medicine | I41: Provisional | J41: T32554MM2121, Period - 03-01-2024 To 02-07-2028 | K41: 7907461354 | L41: 04782872129 | M41: sunithamotty@rediffmail.com | N41: Yes
A42: NEW MICROLAB LABORATORIES | B42: Microlab laboratories , althara junction, chengannur | C42: Alappuzha | D42: 689121 | E42: Medium | F42: NEW MICROLAB LABORATORIES Microlab laboratories, althara junction, chengannur Kerala, Alappuzha - 689121 | G42: Both Laboratory and Diagnostic Imaging Centre | H42: Modern Medicine | I42: Provisional | J42: T32554MM12769, Period - 26-06-2024 To 25-12-2028 | K42: 8078067774 | L42: 04682257728 | M42: microlabcngroffice@gmail.com | N42: Yes
A43: New Microlab Laboratories | B43: Modiuzhathil Building, Althara jn:, Chengannur, Alappuzha | C43: Alappuzha | D43: 689121 | E43: Low | F43: New Microlab Laboratories Modiuzhathil Building, Althara jn:, Chengannur Kerala, Alappuzha - 689121 | G43: Both Laboratory and Diagnostic Imaging Centre | H43: Modern Medicine | I43: Provisional | J43: T32554MMBOTH00015, Period - 19-03-2020 To 18-09-2024 | K43: 9495914402 | L43: 04792455227 | M43: microlabcngr@gmail.com | N43: Yes
A44: S K DIAGNOSTIC CENTRE | B44: S K TOWER, NEAR TALUK HOSPITAL, HARIPPAD | C44: Alappuzha | E44: No PIN | F44: S K DIAGNOSTIC CENTRE S K TOWER, NEAR TALUK HOSPITAL, HARIPPAD Kerala, Alappuzha | G44: Both Laboratory and Diagnostic Imaging Centre | H44: Modern Medicine | I44: Provisional | J44: T32554MM2659, Period - 18-01-2024 To 17-07-2028 | K44: 8921926459 | L44: 08921926459 | M44: skdiagnosticcentreharipad@gmail.com | N44: Yes
A45: S T M LAB | B45: S T M LAB, NEAR MEDICAL COLLEGE, VANDANAM | C45: Alappuzha | E45: No PIN | F45: S T M LAB S T M LAB, NEAR MEDICAL COLLEGE, VANDANAM Kerala, Alappuzha | G45: Both Laboratory and Diagnostic Imaging Centre | H45: Modern Medicine | I45: Provisional | J45: T32554MMBOTH00002, Period - 19-09-2019 To 18-03-2024 | K45: 7025684625 | M45: biocurespecility@gmail.com | N45: Yes
A46: SANJEEVANI LABS | B46: IV/323 A, NEAR HEAD POST OFFICE, CHERTHALA .ALAPUZHA | C46: Alappuzha | D46: 688524 | E46: Medium | F46: SANJEEVANI LABS IV/323 A, NEAR HEAD POST OFFICE, CHERTHALA .ALAPUZHA Kerala, Alappuzha - 688524 | G46: Both Laboratory and Diagnostic Imaging Centre | H46: Modern Medicine | I46: Provisional | J46: T32554MMBOTH00003, Period - 02-10-2019 To 01-04-2024 | K46: 9526791777 | L46: 04782813144 | M46: jasmianush@gmail.com | N46: Yes
A47: SANKARS HEALTH CARE SCANS & DIAGNOSTICS | B47: Kannampallil Building, Near MCH Main Gate, Vandanam, Alappuzha | C47: Alappuzha | D47: 688001 | E47: Medium | F47: SANKARS HEALTH CARE SCANS & DIAGNOSTICS Kannampallil Building, Near MCH Main Gate, Vandanam Kerala, Alappuzha - 688001 | G47: Both Laboratory and Diagnostic Imaging Centre | H47: Modern Medicine | I47: Provisional | J47: T32554MMBOTH00020, Period - 23-12-2021 To 22-06-2026 | K47: 9947034488 | M47: shcbdm@gmail.com | N47: Yes
A48: SANKARS HEALTH CARE SCANS AND DIAGNOSTICS A UNIT OF SANKARS SCANS AND DIAGNOSTICS PVT LTD | B48: OPP GOVT WEST UP SCHOOL, NEAR GOVT TALUK HOSPITAL, THURAVOOR | C48: Alappuzha | D48: 688532 | E48: Medium | F48: SANKARS HEALTH CARE SCANS AND DIAGNOSTICS A UNIT OF SANKARS SCANS AND DIAGNOSTICS PVT LTD OPP GOVT WEST UP SCHOOL, NEAR GOVT TALUK HOSPITAL, THURAVOOR Kerala, Alappuzha - 688532 | G48: Both Laboratory and Diagnostic Imaging Centre | H48: Modern Medicine | I48: Permanent | J48: P32554MM2858, Period - 11-02-2025 To 10-02-2030 | K48: 9995011488 | L48: 09995011488 | M48: shcdthuravoor@gmail.com | N48: Yes
A49: SANKARS HEALTH CARE SCANS AND DIAGNOSTICS A UNIT OF SANKARS SCANS AND DIAGNOSTICS PVT LTD | B49: OASIS TOWER , MUNICIPAL TOWN HALL ROAD , KAYAMKULAM | C49: Alappuzha | D49: 690502 | E49: Medium | F49: SANKARS HEALTH CARE SCANS AND DIAGNOSTICS A UNIT OF SANKARS SCANS AND DIAGNOSTICS PVT LTD OASIS TOWER, MUNICIPAL TOWN HALL ROAD, KAYAMKULAM Kerala, Alappuzha - 690502 | G49: Both Laboratory and Diagnostic Imaging Centre | H49: Modern Medicine | I49: Permanent | J49: P32554MM2860, Period - 11-02-2025 To 10-02-2030 | K49: 9526064488 | L49: 09526064488 | M49: shcdkayamkulam@gmail.com | N49: Yes
A50: SANKARS HEALTHCARE SCANS AND DIAGNOSTICS | B50: OPP. T D SCHOOL, ALAPUZHA | C50: Alappuzha | E50: No PIN | F50: SANKARS HEALTHCARE SCANS AND DIAGNOSTICS OPP. T D SCHOOL, ALAPUZHA Kerala, Alappuzha | G50: Both Laboratory and Diagnostic Imaging Centre | H50: Modern Medicine | I50: Provisional | J50: T32554MM281, Period - 18-04-2023 To 17-10-2027 | K50: 9447041229 | L50: 04772963000 | M50: shcbdm@gmail.com | N50: Yes
A51: SANKARS HEALTHCARE SCANS AND DIAGNOSTICS | B51: Bolla House, Near Mini Civil station, Cherthala , Alappuzha | C51: Alappuzha | D51: 688001 | E51: Low | F51: SANKARS HEALTHCARE SCANS AND DIAGNOSTICS Bolla House, Near Mini Civil station, Cherthala Kerala, Alappuzha - 688001 | G51: Both Laboratory and Diagnostic Imaging Centre | H51: Modern Medicine | I51: Provisional | J51: T32554MM483, Period - 23-05-2023 To 22-11-2027 | K51: 9447041229 | L51: 04782812268 | M51: shcbdm@gmail.com | N51: Yes
A52: SONIA CLINICAL LABORATORY AND ECG | B52: NEAR GOVT. HOSPITAL, MUHAMMA, MUHAMMA.P.O.CHERTHLA, ALAPPUZHA | C52: Alappuzha | D52: 688525 | E52: High | F52: SONIA CLINICAL LABORATORY AND ECG NEAR GOVT. HOSPITAL, MUHAMMA, MUHAMMA.P.O.CHERTHLA Kerala, Alappuzha - 688525 | G52: Both Laboratory and Diagnostic Imaging Centre | H52: Modern Medicine | I52: Provisional | J52: T32554MM3005, Period - 24-01-2024 To 23-07-2028 | K52: 8547718945 | L52: 04782868945 | M52: sonialab1988@gnail.com | N52: Yes
A53: ST ANTONYS X RAY ECG AND LABS | B53: CHETTICADU , PATHIRAPALLY PO , ALAPPUZHA | C53: Alappuzha | D53: 688521 | E53: High | F53: ST ANTONYS X RAY ECG AND LABS CHETTICADU, PATHIRAPALLY PO Kerala, Alappuzha - 688521 | G53: Both Laboratory and Diagnostic Imaging Centre | H53: Modern Medicine | I53: Provisional | J53: T32554MM1779, Period - 27-12-2023 To 26-06-2028 | K53: 9567168920 | L53: 09567168920 | M53: jessyjijo85@gmail.com | N53: Yes
A54: Santhwanam Medical Laboratary | B54: 233A Rajasudha Building Poochakkal P O | C54: Alappuzha | D54: 688526 | E54: High | F54: Santhwanam Medical Laboratary 233A Rajasudha Building Poochakkal P O Kerala, Alappuzha - 688526 | G54: Both Laboratory and Diagnostic Imaging Centre | H54: Modern Medicine | I54: Permanent | J54: P32554MM6410, Period - 16-03-2026 To 16-03-2031 | K54: 9048403279 | L54: 04782816919 | M54: santhwanammedlab@gmail.com | N54: Yes
A55: Trivandrum Scans And Diagnostic Centre | B55: Opp KSRTC Terminal , Haripad | C55: Alappuzha | D55: 690514 | E55: Medium | F55: Trivandrum Scans And Diagnostic Centre Opp KSRTC Terminal, Haripad Kerala, Alappuzha - 690514 | G55: Both Laboratory and Diagnostic Imaging Centre | H55: Modern Medicine | I55: Provisional | J55: T32554MM4147, Period - 29-01-2024 To 28-07-2028 | K55: 9447667101 | L55: 04792416701 | M55: tvmscans@gmai.com | N55: Yes
A56: ddrc agilus pathlabs ltd | B56: Near Govt hospital Mavelikkara | C56: Alappuzha | E56: No PIN | F56: ddrc agilus pathlabs ltd Near Govt hospital Mavelikkara Kerala, Alappuzha | G56: Both Laboratory and Diagnostic Imaging Centre | H56: Modern Medicine | I56: Permanent | J56: P32554MM6298, Period - 11-03-2026 To 11-03-2031 | K56: 9778609934 | L56: 09778609934 | M56: mavelikkara.ddrc@agilus.in | N56: Yes
A57: ddrc agilus pathlabs ltd | B57: Opposite govt hospital Chengannur | C57: Alappuzha | D57: 689121 | E57: Medium | F57: ddrc agilus pathlabs ltd Opposite govt hospital Chengannur Kerala, Alappuzha - 689121 | G57: Both Laboratory and Diagnostic Imaging Centre | H57: Modern Medicine | I57: Permanent | J57: P32554MM8146, Period - 17-04-2026 To 17-04-2031 | K57: 9072570815 | L57: 09072570815 | M57: chengannur.ddrc@agilus.in | N57: Yes
A58: ddrc agilus pathlabs ltd | B58: Opposite KSRTC bus stand harippad | C58: Alappuzha | E58: No PIN | F58: ddrc agilus pathlabs ltd Opposite KSRTC bus stand harippad Kerala, Alappuzha | G58: Both Laboratory and Diagnostic Imaging Centre | H58: Modern Medicine | I58: Permanent | J58: P32554MM8264, Period - 20-04-2026 To 20-04-2031 | K58: 9778609938 | L58: 09778609938 | M58: harippad.ddrc@agilus.in | N58: Yes
A59: ddrc agilus pathlabs ltd | B59: Srambical building near chakkulamdevi temple | C59: Alappuzha | E59: No PIN | F59: ddrc agilus pathlabs ltd Srambical building near chakkulamdevi temple Kerala, Alappuzha | G59: Both Laboratory and Diagnostic Imaging Centre | H59: Modern Medicine | I59: Permanent | J59: P32554MM8266, Period - 20-04-2026 To 20-04-2031 | K59: 8590603316 | L59: 08590603316 | M59: chakkulathkavu.ddrc@agilus.in | N59: Yes
A60: kochin lab and x-Ray | B60: KOCHIN LAB AND X-RAY, PRABHA COMPLEX, WEST OF PALLIMUK JN, VANDANAM | C60: Alappuzha | E60: No PIN | F60: kochin lab and x-Ray KOCHIN LAB AND X-RAY, PRABHA COMPLEX, WEST OF PALLIMUK JN, VANDANAM Kerala, Alappuzha | G60: Both Laboratory and Diagnostic Imaging Centre | H60: Modern Medicine | I60: Provisional | J60: T32554MMBOTH00011, Period - 29-01-2020 To 28-07-2024 | K60: 9846104086 | M60: appus86@gmail.com | N60: Yes
A61: CRESCENT MEDI CLINIC | B61: CRESCENT MEDI CLINIC , NEAR KANJIPPUZHA MUSLIM JAMAATH MOSQUE , KANJIPPUZHA , VALLIKUNNAM PO | C61: Alappuzha | D61: 690501 | E61: High | F61: CRESCENT MEDI CLINIC CRESCENT MEDI CLINIC, NEAR KANJIPPUZHA MUSLIM JAMAATH MOSQUE, KANJIPPUZHA, VALLIKUNNAM PO Kerala, Alappuzha - 690501 | G61: Day Care Centre | H61: Modern Medicine | I61: Provisional | J61: T32554MM4237, Period - 29-01-2024 To 28-07-2028 | K61: 8714530575 | L61: 04792995981 | M61: crescentmediclinic@gmail.com | N61: Yes
A62: DOCTORS CLINIC | B62: Opp St George Orthodox Church , Pallipad | C62: Alappuzha | D62: 690512 | E62: Medium | F62: DOCTORS CLINIC Opp St George Orthodox Church, Pallipad Kerala, Alappuzha - 690512 | G62: Day Care Centre | H62: Ayurveda | I62: Provisional | J62: T32554AY13799, Period - 10-03-2026 To 09-09-2030 | K62: 9567906213 | L62: 04792409333 | M62: drshyla66@gmail.com | N62: Yes
A63: DOCTORS CLINIC | B63: Kollamparampil Building , Paypad | C63: Alappuzha | E63: No PIN | F63: DOCTORS CLINIC Kollamparampil Building, Paypad Kerala, Alappuzha | G63: Day Care Centre | H63: Ayurveda | I63: Provisional | J63: T32554AY13801, Period - 10-03-2026 To 09-09-2030 | K63: 9567906213 | L63: 04792409333 | M63: drshyla66@gmail.com | N63: Yes
A64: Dr Ishas skin Care Centre | B64: Chakkarakulam Road , east of Boys School , Cherthala | C64: Alappuzha | D64: 688524 | E64: Medium | F64: Dr Ishas skin Care Centre Chakkarakulam Road, east of Boys School, Cherthala Kerala, Alappuzha - 688524 | G64: Day Care Centre | H64: Modern Medicine | I64: Permanent | J64: P32554MM7542, Period - 31-03-2026 To 31-03-2031 | K64: 9947275011 | L64: 08589015011 | M64: ishavinay@hotmail.com | N64: Yes
A65: Dr Oommens Eye Hospital and Micro Surgery Centre | B65: Dr. Oommen's Eye Hospital, Thamarasseril Building, Temple Road | C65: Alappuzha | E65: No PIN | F65: Dr Oommens Eye Hospital and Micro Surgery Centre Dr. Oommen's Eye Hospital, Thamarasseril Building, Temple Road Kerala, Alappuzha | G65: Day Care Centre | H65: Modern Medicine | I65: Provisional | J65: T32554MMDC00002, Period - 05-09-2022 To 04-03-2027 | K65: 9072234433 | L65: 04792453416 | M65: drommenvarghese@gmail.com | N65: Yes
A66: Dr SHYLAS SKIN AND COSMETIC CLINIC | B66: TAJ AUDITORIUM , KAREELAKULANGARA | C66: Alappuzha | D66: 690572 | E66: Medium | F66: Dr SHYLAS SKIN AND COSMETIC CLINIC TAJ AUDITORIUM, KAREELAKULANGARA Kerala, Alappuzha - 690572 | G66: Day Care Centre | H66: Ayurveda | I66: Provisional | J66: T32554AY13805, Period - 10-03-2026 To 09-09-2030 | K66: 9567906213 | L66: 04792409333 | M66: drshyla66@gmail.com | N66: Yes
A67: GOLDEN FLOWER MEDICAL CENTRE | B67: GOLDEN FLOWER MEDICAL CENTRE, ADIVARAM, MANNANCHERRY P O. | C67: Alappuzha | E67: No PIN | F67: GOLDEN FLOWER MEDICAL CENTRE GOLDEN FLOWER MEDICAL CENTRE, ADIVARAM, MANNANCHERRY P O. Kerala, Alappuzha | G67: Day Care Centre | H67: Modern Medicine | I67: Permanent | J67: P32554MM7076, Period - 26-03-2026 To 26-03-2031 | K67: 9496333374 | L67: 04772970257 | M67: dhruvinil@gmail.com | N67: Yes
A68: HEALTHPARK MEDICAL CENTRE | B68: EMS STADIUM COMPLEX, ALAPPUZHA | C68: Alappuzha | D68: 688001 | E68: Medium | F68: HEALTHPARK MEDICAL CENTRE EMS STADIUM COMPLEX Kerala, Alappuzha - 688001 | G68: Day Care Centre | H68: Modern Medicine | I68: Provisional | J68: T32554MM2093, Period - 01-01-2024 To 30-06-2028 | K68: 9072177771 | L68: 04772250000 | M68: healthparkalpy@gmail.com | N68: Yes
A69: OPSIN HEALTH CARE PVT. LTD. | B69: swathy complex , opp.muncipality , Mavelikara | C69: Alappuzha | E69: No PIN | F69: OPSIN HEALTH CARE PVT. LTD. swathy complex, opp.muncipality, Mavelikara Kerala, Alappuzha | G69: Day Care Centre | H69: Modern Medicine | I69: Provisional | J69: T32554MMDC00001, Period - 01-01-2022 To 30-06-2026 | K69: 8138947477 | M69: preciseeye1knpy@gmail.com | N69: Yes
A70: A J DENTAL CLINIC | B70: A J DENTAL CLINIC , KIZHAKENADA PULIYOOR TEMPLE , PULIYOOR, ALAPUZHA DIST, KERALA | C70: Alappuzha | D70: 689510 | E70: Medium | F70: A J DENTAL CLINIC A J DENTAL CLINIC, KIZHAKENADA PULIYOOR TEMPLE, PULIYOOR, ALAPUZHA DIST Kerala, Alappuzha - 689510 | G70: Dental | H70: Modern Medicine | I70: Provisional | J70: T32554MM4457, Period - 29-01-2024 To 28-07-2028 | K70: 9048690958 | L70: 09447776725 | M70: immanuelkurianmathew@gmail.com | N70: Yes
A71: A R Dental Hub | B71: A R DENTAL HUB , NEAR BSNL OFFICE , HARIPAD | C71: Alappuzha | D71: 690514 | E71: Medium | F71: A R Dental Hub A R DENTAL HUB, NEAR BSNL OFFICE, HARIPAD Kerala, Alappuzha - 690514 | G71: Dental | H71: Modern Medicine | I71: Provisional | J71: T32554MM4443, Period - 29-01-2024 To 28-07-2028 | K71: 9496547963 | L71: 09496547963 | M71: arathi.s.mohan@gmail.com | N71: Yes
A72: ADAMUKKATH DENTAL CLINIC | B72: ADAMUKKATH DENTAL CLINIC , T D ROAD , NORTH OF TD TEMPLE, CHERTHALA | C72: Alappuzha | D72: 688524 | E72: Medium | F72: ADAMUKKATH DENTAL CLINIC ADAMUKKATH DENTAL CLINIC, T D ROAD, NORTH OF TD TEMPLE, CHERTHALA Kerala, Alappuzha - 688524 | G72: Dental | H72: Modern Medicine | I72: Provisional | J72: T32554MM4283, Period - 29-01-2024 To 28-07-2028 | K72: 8156872654 | L72: 09447712961 | M72: jdshenoy@gmail.com | N72: Yes
A73: AESTHETIC DENTAL CLINIC | B73: AESTHETIC DENTAL CLINIC, BHASKARA TOWER, PRAIKARA, MAVELIKARA P.O | C73: Alappuzha | E73: No PIN | F73: AESTHETIC DENTAL CLINIC AESTHETIC DENTAL CLINIC, BHASKARA TOWER, PRAIKARA, MAVELIKARA P.O Kerala, Alappuzha | G73: Dental | H73: Modern Medicine | I73: Provisional | J73: T32554MM9791, Period - 11-03-2024 To 10-09-2028 | K73: 7736522072 | L73: 09400081814 | M73: senanmanju@gmail.com | N73: Yes
A74: ALPHA DENTAL CARE | B74: CANAL JUNCTION, PENNUKARA | C74: Alappuzha | E74: No PIN | F74: ALPHA DENTAL CARE CANAL JUNCTION, PENNUKARA Kerala, Alappuzha | G74: Dental | H74: Modern Medicine | I74: Provisional | J74: T32554MM4389, Period - 29-01-2024 To 28-07-2028 | K74: 9037080197 | L74: 04792080497 | M74: alphadentalcare2022@gmail.com | N74: Yes
A75: ALSHIFA DENTAL CARE | B75: 6 43 A NEAR TO 1008 SOCIETY 1008 JN ALAPPUZHA | C75: Alappuzha | D75: 688001 | E75: Medium | F75: ALSHIFA DENTAL CARE 6 43 A NEAR TO 1008 SOCIETY 1008 JN Kerala, Alappuzha - 688001 | G75: Dental | H75: Modern Medicine | I75: Permanent | J75: P32554MM4120, Period - 14-05-2025 To 14-05-2030 | K75: 8943263899 | L75: 09048137406 | M75: dr.saniyasen@gmail.com | N75: Yes
A76: ALSHIFA DENTAL CLINIC | B76: ALSHIFA DENTAL CLINIC, MIRSAD ROAD, VADUTHALA JN , AROOKUTTY | C76: Alappuzha | D76: 688535 | E76: Medium | F76: ALSHIFA DENTAL CLINIC ALSHIFA DENTAL CLINIC, MIRSAD ROAD, VADUTHALA JN, AROOKUTTY Kerala, Alappuzha - 688535 | G76: Dental | H76: Modern Medicine | I76: Provisional | J76: T32554MM5437, Period - 06-02-2024 To 05-08-2028 | K76: 8943263899 | L76: 08943263899 | M76: dr.saniyasen@gmail.com | N76: Yes
A77: AMALA DENTAL SPECIALITY CENTRE | B77: AMALA DENTAL SPECIALITY CENTRE , CHURCH ROAD , IRON BRIDGE PO , ALAPPUZHA 688011 | C77: Alappuzha | D77: 688011 | E77: High | F77: AMALA DENTAL SPECIALITY CENTRE AMALA DENTAL SPECIALITY CENTRE, CHURCH ROAD, IRON BRIDGE PO Kerala, Alappuzha - 688011 | G77: Dental | H77: Modern Medicine | I77: Provisional | J77: T32554MM5603, Period - 06-02-2024 To 05-08-2028 | K77: 9497866102 | L77: 04772262428 | M77: annujatomy99@gmail.com | N77: Yes
A78: AMBOOKENS SPECIALITY DENTAL CLINIC | B78: Building No.76 in Ward 5, Aroor, Alappuzha | C78: Alappuzha | D78: 688001 | E78: Low | F78: AMBOOKENS SPECIALITY DENTAL CLINIC Building No.76 in Ward 5, Aroor Kerala, Alappuzha - 688001 | G78: Dental | H78: Modern Medicine | I78: Provisional | J78: T32554MM5539, Period - 06-02-2024 To 05-08-2028 | K78: 9846053901 | L78: 04782876177 | M78: jose2ambooken@gmail.com | N78: Yes
A79: AMBOOKENS SPECIALITY DENTAL CLINIC | B79: Ward 15, building 413414, Al Ishan Shopping Complex, Chandiroor, Alappuzha | C79: Alappuzha | D79: 688001 | E79: Medium | F79: AMBOOKENS SPECIALITY DENTAL CLINIC Ward 15, building 413414, Al Ishan Shopping Complex, Chandiroor Kerala, Alappuzha - 688001 | G79: Dental | H79: Modern Medicine | I79: Provisional | J79: T32554MM5545, Period - 06-02-2024 To 05-08-2028 | K79: 9846053901 | L79: 04782876177 | M79: jose2ambooken@gmail.com | N79: Yes
A80: AMEYAA MULTI SPECIALITY DENTAL CLINIC | B80: GLAS tower, T.A Ali Akbar road, near town hall, kayamkulam | C80: Alappuzha | D80: 690502 | E80: Medium | F80: AMEYAA MULTI SPECIALITY DENTAL CLINIC GLAS tower, T.A Ali Akbar road, near town hall, kayamkulam Kerala, Alappuzha - 690502 | G80: Dental | H80: Modern Medicine | I80: Provisional | J80: T32554MM5515, Period - 06-02-2024 To 05-08-2028 | K80: 7907330147 | L80: 04792443723 | M80: ameyaadentalclinic@gmail.com | N80: Yes
A81: AMRITA DENTAL CLINIC | B81: Devaswom Board Shopping Complex, Mavelikara | C81: Alappuzha | E81: No PIN | F81: AMRITA DENTAL CLINIC Devaswom Board Shopping Complex, Mavelikara Kerala, Alappuzha | G81: Dental | H81: Modern Medicine | I81: Provisional | J81: T32554MM5495, Period - 06-02-2024 To 05-08-2028 | K81: 9447103758 | L81: 04792304828 | M81: krishnarajnair99@gmail.com | N81: Yes
A82: ANAND DENTAL SPECIALTY CENTRE | B82: PAPPANS ARCADE , NEAR MANORAMA JUNCTION , CHERTHALA | C82: Alappuzha | D82: 688524 | E82: Medium | F82: ANAND DENTAL SPECIALTY CENTRE PAPPANS ARCADE, NEAR MANORAMA JUNCTION, CHERTHALA Kerala, Alappuzha - 688524 | G82: Dental | H82: Modern Medicine | I82: Provisional | J82: T32554MM5519, Period - 06-02-2024 To 05-08-2028 | K82: 9847388791 | L82: 04782813908 | M82: gvggym@gmail.com | N82: Yes
A83: ANJALI DENTAL CLINIC | B83: SOUPARNIKA WARD 6 SOUTH OF VRVM SCHOOL VAYALAR P O | C83: Alappuzha | D83: 688536 | E83: High | F83: ANJALI DENTAL CLINIC SOUPARNIKA WARD 6 SOUTH OF VRVM SCHOOL VAYALAR P O Kerala, Alappuzha - 688536 | G83: Dental | H83: Modern Medicine | I83: Provisional | J83: T32554MM5501, Period - 06-02-2024 To 05-08-2028 | K83: 9895775295 | L83: 09447462778 | M83: drvandanatr@gmail.com | N83: Yes
A84: APOLLO SMILE CARE | B84: APOLLO SMILE CARE , KALAVOOR P O | C84: Alappuzha | D84: 688522 | E84: High | F84: APOLLO SMILE CARE APOLLO SMILE CARE, KALAVOOR P O Kerala, Alappuzha - 688522 | G84: Dental | H84: Modern Medicine | I84: Permanent | J84: P32554MM7296, Period - 28-03-2026 To 28-03-2031 | K84: 6282369851 | L84: 06282369851 | M84: avinashsarathkumar.11@gmail.com | N84: Yes
A85: ASPIRE DENTAL AND MEDICAL HEALTH CARE | B85: Aspire dental and medical health care, Palesseril arcade, chirakadavom, kayamkulam, alapuzha | C85: Alappuzha | D85: 690502 | E85: Medium | F85: ASPIRE DENTAL AND MEDICAL HEALTH CARE Aspire dental and medical health care, Palesseril arcade, chirakadavom, kayamkulam, alapuzha Kerala, Alappuzha - 690502 | G85: Dental | H85: Modern Medicine | I85: Provisional | J85: T32554MM4277, Period - 29-01-2024 To 28-07-2028 | K85: 9847222722 | L85: 04792441144 | M85: dr.anandraj.8939@gmail.com | N85: Yes
A86: ASTER DENTAL CLINIC | B86: kalayakattu building, leprosy hospital junction, kalavoor po alappuzha | C86: Alappuzha | D86: 688522 | E86: High | F86: ASTER DENTAL CLINIC kalayakattu building, leprosy hospital junction, kalavoor po Kerala, Alappuzha - 688522 | G86: Dental | H86: Modern Medicine | I86: Provisional | J86: T32554MM4167, Period - 29-01-2024 To 28-07-2028 | K86: 9188332267 | L86: 09188223378 | M86: dentalclinicaster@gmail.com | N86: Yes
A87: ASTER DENTAL CLINIC | B87: PANICKERS BUILDING , KIDANGARA PO , ALAPPUZHA | C87: Alappuzha | D87: 688001 | E87: Medium | F87: ASTER DENTAL CLINIC PANICKERS BUILDING, KIDANGARA PO Kerala, Alappuzha - 688001 | G87: Dental | H87: Modern Medicine | I87: Provisional | J87: T32554MM4471, Period - 29-01-2024 To 28-07-2028 | K87: 7994414468 | L87: 08075878125 | M87: ASTERKIDANGARA@GMAIL.COM | N87: Yes
A88: ASTER DENTAL CLINIC | B88: makayiram building, nediyani, valavanad, alappuzha | C88: Alappuzha | D88: 688001 | E88: Medium | F88: ASTER DENTAL CLINIC makayiram building, nediyani, valavanad Kerala, Alappuzha - 688001 | G88: Dental | H88: Modern Medicine | I88: Provisional | J88: T32554MM4481, Period - 29-01-2024 To 28-07-2028 | K88: 8547733588 | L88: 08547722188 | M88: dentalclinicaster2@gmail.com | N88: Yes
A89: ASWATHI DENTAL CLINIC | B89: Aswathi, Thuravoor P.O., Cherthala | C89: Alappuzha | D89: 688532 | E89: High | F89: ASWATHI DENTAL CLINIC Aswathi, Thuravoor P.O., Cherthala Kerala, Alappuzha - 688532 | G89: Dental | H89: Modern Medicine | I89: Provisional | J89: T32554MM5443, Period - 06-02-2024 To 05-08-2028 | K89: 9847062376 | L89: 04782562376 | M89: shilpaaniyan@gmail.com | N89: Yes
A90: AVENUES DENTAL | B90: court road, near kaniza bridge , kayamkulam | C90: Alappuzha | D90: 690502 | E90: Medium | F90: AVENUES DENTAL court road, near kaniza bridge, kayamkulam Kerala, Alappuzha - 690502 | G90: Dental | H90: Modern Medicine | I90: Provisional | J90: T32554MM4445, Period - 29-01-2024 To 28-07-2028 | K90: 9995743881 | L90: 09986606405 | M90: drdhanya99@gmail.com | N90: Yes
A91: Abhilash Dental Clinic | B91: Abhilash dental clinic , 202-A, CMC-13 , South of Taluk Hospital, Cherthala. | C91: Alappuzha | D91: 688524 | E91: Medium | F91: Abhilash Dental Clinic Abhilash dental clinic, 202-A, CMC-13, South of Taluk Hospital, Cherthala. Kerala, Alappuzha - 688524 | G91: Dental | H91: Modern Medicine | I91: Provisional | J91: T32554MM4257, Period - 29-01-2024 To 28-07-2028 | K91: 9447224088 | L91: 04782862677 | M91: abhilashku@gmail.com | N91: Yes
A92: Advanced Dental Care | B92: Cullen Road , Vazhicherry Ward , Alappuzha | C92: Alappuzha | D92: 688001 | E92: Medium | F92: Advanced Dental Care Cullen Road, Vazhicherry Ward Kerala, Alappuzha - 688001 | G92: Dental | H92: Modern Medicine | I92: Provisional | J92: T32554MM4423, Period - 29-01-2024 To 28-07-2028 | K92: 9961473479 | L92: 04772243479 | M92: binsmath@gmail.com | N92: Yes
A93: Aesthetic Dental Clinic | B93: Aesthetic Dental Clinic , Mannil building, Near Union Bank, Chengannur.p.o | C93: Alappuzha | D93: 689121 | E93: High | F93: Aesthetic Dental Clinic Aesthetic Dental Clinic, Mannil building, Near Union Bank, Chengannur.p.o Kerala, Alappuzha - 689121 | G93: Dental | H93: Modern Medicine | I93: Provisional | J93: T32554MM5523, Period - 06-02-2024 To 05-08-2028 | K93: 9495248640 | L93: 04792456644 | M93: serenasusangeorge@gmail.com | N93: Yes
... A97: CARE DENTAL CLINIC | B97: VADAKEDATHU BUILDING , THITTAMEL , CHENGANNUR | C97: Alappuzha | D97: 689121 | E97: Medium | F97: CARE DENTAL CLINIC VADAKEDATHU BUILDING, THITTAMEL, CHENGANNUR Kerala, Alappuzha - 689121 | G97: Dental | H97: Modern Medicine | I97: Provisional | J97: T32554MM4323, Period - 29-01-2024 To 28-07-2028 | K97: 8075900239 | L97: 06282260149 | M97: linimjojasa@gmail.com | N97: Yes
A98: CARE32DENTAL CLINIC | B98: ADARSH BUILDING , CHUNAKKARA NADUVIL , CHUNAKKARA P O | C98: Alappuzha | E98: No PIN | F98: CARE32DENTAL CLINIC ADARSH BUILDING, CHUNAKKARA NADUVIL, CHUNAKKARA P O Kerala, Alappuzha | G98: Dental | H98: Modern Medicine | I98: Permanent | J98: P32554MM8902, Period - 16-05-2026 To 16-05-2031 | K98: 7356069851 | L98: 04792385372 | M98: rahimrehila542@gmail.com | N98: Yes
A99: CAREWELL MULTISPECIALITY DENTAL CLINIC AND IMPLANT CENTRE | B99: CHACKOLIL BUILDING, VP XI -326, NEAR VEEYAPURAM PANCHAYATH OFFICE, PAYIPAD.P.O, HARIPPAD, ALAPPUZHA | C99: Alappuzha | D99: 690556 | E99: High | F99: CAREWELL MULTISPECIALITY DENTAL CLINIC AND IMPLANT CENTRE CHACKOLIL BUILDING, VP XI -326, NEAR VEEYAPURAM PANCHAYATH OFFICE, PAYIPAD.P.O, HARIPPAD Kerala, Alappuzha - 690556 | G99: Dental | H99: Modern Medicine | I99: Provisional | J99: T32554MM4459, Period - 29-01-2024 To 28-07-2028 | K99: 9562977561 | L99: 09562977561 | M99: jerrythomas1011@gmail.com | N99: Yes
A100: CHARUMMOODU SPECIALITY DENTAL CLINIC | B100: Charummoodu Speciality Dental Clinic , Near Federal Bank , Charummoodu , Mavelikkara , Alappuzha dt. | C100: Alappuzha | D100: 688001 | E100: Medium | F100: CHARUMMOODU SPECIALITY DENTAL CLINIC Charummoodu Speciality Dental Clinic, Near Federal Bank, Charummoodu, Mavelikkara, Alappuzha dt. Kerala, Alappuzha - 688001 | G100: Dental | H100: Modern Medicine | I100: Provisional | J100: T32554MM4299, Period - 29-01-2024 To 28-07-2028 | K100: 9447866849 | L100: 09447866849 | M100: chandranakhilesh@gmail.com | N100: Yes
A101: CHELLAMANGALATHU DENTAL CARE | B101: CHELLAMANGALATHU DENTAL CARE , KENZA MALL CHARUMMOODU , ALAPPUZHA DISTRICT | C101: Alappuzha | D101: 688001 | E101: Medium | F101: CHELLAMANGALATHU DENTAL CARE CHELLAMANGALATHU DENTAL CARE, KENZA MALL CHARUMMOODU, ALAPPUZHA DISTRICT Kerala, Alappuzha - 688001 | G101: Dental | H101: Modern Medicine | I101: Permanent | J101: P32554MM1142, Period - 22-08-2024 To 21-08-2029 | K101: 6362978858 | L101: 04734288889 | M101: drpriyanitin@gmail.com | N101: Yes
A102: CHITHIRA DENTAL CLINIC and ORTHODONTIC CENTRE | B102: Chithira Dental Clinic And Orthodontic Centre , Karakkad , Chengannur | C102: Alappuzha | D102: 689121 | E102: Low | F102: CHITHIRA DENTAL CLINIC and ORTHODONTIC CENTRE Chithira Dental Clinic And Orthodontic Centre, Karakkad, Chengannur Kerala, Alappuzha - 689121 | G102: Dental | H102: Modern Medicine | I102: Provisional | J102: T32554MM5479, Period - 06-02-2024 To 05-08-2028 | K102: 9400309090 | L102: 09400309090 | M102: arunctra@gmail.com | N102: Yes
A103: COSMETIC DENTAL CLINIC | B103: MUTHOOT SHOPPING CENTRE, KAYAMKULAM | C103: Alappuzha | D103: 690502 | E103: Medium | F103: COSMETIC DENTAL CLINIC MUTHOOT SHOPPING CENTRE, KAYAMKULAM Kerala, Alappuzha - 690502 | G103: Dental | H103: Modern Medicine | I103: Permanent | J103: P32554MM7502, Period - 30-03-2026 To 30-03-2031 | K103: 9074125520 | L103: 09074125520 | M103: sheenamathew72@gmail.com | N103: Yes
...

Sheet Summary
A1: Establishments by district and PIN confidence
A3: District | B3: High | C3: Medium | D3: Low | E3: No PIN | F3: Total
A4: Alappuzha | B4: =COUNTIFS('Mail List'!$C$2:$C$12307,$A4,'Mail List'!$E$2:$E$12307,B$3) -> 213 | C4: =COUNTIFS('Mail List'!$C$2:$C$12307,$A4,'Mail List'!$E$2:$E$12307,C$3) -> 352 | D4: =COUNTIFS('Mail List'!$C$2:$C$12307,$A4,'Mail List'!$E$2:$E$12307,D$3) -> 99 | E4: =COUNTIFS('Mail List'!$C$2:$C$12307,$A4,'Mail List'!$E$2:$E$12307,E$3) -> 192 | F4: =SUM(B4:E4) -> 856
A5: Ernakulam | B5: =COUNTIFS('Mail List'!$C$2:$C$12307,$A5,'Mail List'!$E$2:$E$12307,B$3) -> 428 | C5: =COUNTIFS('Mail List'!$C$2:$C$12307,$A5,'Mail List'!$E$2:$E$12307,C$3) -> 661 | D5: =COUNTIFS('Mail List'!$C$2:$C$12307,$A5,'Mail List'!$E$2:$E$12307,D$3) -> 94 | E5: =COUNTIFS('Mail List'!$C$2:$C$12307,$A5,'Mail List'!$E$2:$E$12307,E$3) -> 638 | F5: =SUM(B5:E5) -> 1821
A6: Idukki | B6: =COUNTIFS('Mail List'!$C$2:$C$12307,$A6,'Mail List'!$E$2:$E$12307,B$3) -> 91 | C6: =COUNTIFS('Mail List'!$C$2:$C$12307,$A6,'Mail List'!$E$2:$E$12307,C$3) -> 55 | D6: =COUNTIFS('Mail List'!$C$2:$C$12307,$A6,'Mail List'!$E$2:$E$12307,D$3) -> 4 | E6: =COUNTIFS('Mail List'!$C$2:$C$12307,$A6,'Mail List'!$E$2:$E$12307,E$3) -> 220 | F6: =SUM(B6:E6) -> 370
A7: Kannur | B7: =COUNTIFS('Mail List'!$C$2:$C$12307,$A7,'Mail List'!$E$2:$E$12307,B$3) -> 206 | C7: =COUNTIFS('Mail List'!$C$2:$C$12307,$A7,'Mail List'!$E$2:$E$12307,C$3) -> 410 | D7: =COUNTIFS('Mail List'!$C$2:$C$12307,$A7,'Mail List'!$E$2:$E$12307,D$3) -> 103 | E7: =COUNTIFS('Mail List'!$C$2:$C$12307,$A7,'Mail List'!$E$2:$E$12307,E$3) -> 244 | F7: =SUM(B7:E7) -> 963
A8: Kasargod | B8: =COUNTIFS('Mail List'!$C$2:$C$12307,$A8,'Mail List'!$E$2:$E$12307,B$3) -> 31 | C8: =COUNTIFS('Mail List'!$C$2:$C$12307,$A8,'Mail List'!$E$2:$E$12307,C$3) -> 126 | D8: =COUNTIFS('Mail List'!$C$2:$C$12307,$A8,'Mail List'!$E$2:$E$12307,D$3) -> 21 | E8: =COUNTIFS('Mail List'!$C$2:$C$12307,$A8,'Mail List'!$E$2:$E$12307,E$3) -> 65 | F8: =SUM(B8:E8) -> 243
A9: Kollam | B9: =COUNTIFS('Mail List'!$C$2:$C$12307,$A9,'Mail List'!$E$2:$E$12307,B$3) -> 220 | C9: =COUNTIFS('Mail List'!$C$2:$C$12307,$A9,'Mail List'!$E$2:$E$12307,C$3) -> 322 | D9: =COUNTIFS('Mail List'!$C$2:$C$12307,$A9,'Mail List'!$E$2:$E$12307,D$3) -> 85 | E9: =COUNTIFS('Mail List'!$C$2:$C$12307,$A9,'Mail List'!$E$2:$E$12307,E$3) -> 240 | F9: =SUM(B9:E9) -> 867
A10: Kottayam | B10: =COUNTIFS('Mail List'!$C$2:$C$12307,$A10,'Mail List'!$E$2:$E$12307,B$3) -> 284 | C10: =COUNTIFS('Mail List'!$C$2:$C$12307,$A10,'Mail List'!$E$2:$E$12307,C$3) -> 299 | D10: =COUNTIFS('Mail List'!$C$2:$C$12307,$A10,'Mail List'!$E$2:$E$12307,D$3) -> 84 | E10: =COUNTIFS('Mail List'!$C$2:$C$12307,$A10,'Mail List'!$E$2:$E$12307,E$3) -> 277 | F10: =SUM(B10:E10) -> 944
A11: Kozhikode | B11: =COUNTIFS('Mail List'!$C$2:$C$12307,$A11,'Mail List'!$E$2:$E$12307,B$3) -> 223 | C11: =COUNTIFS('Mail List'!$C$2:$C$12307,$A11,'Mail List'!$E$2:$E$12307,C$3) -> 264 | D11: =COUNTIFS('Mail List'!$C$2:$C$12307,$A11,'Mail List'!$E$2:$E$12307,D$3) -> 36 | E11: =COUNTIFS('Mail List'!$C$2:$C$12307,$A11,'Mail List'!$E$2:$E$12307,E$3) -> 440 | F11: =SUM(B11:E11) -> 963
A12: Malappuram | B12: =COUNTIFS('Mail List'!$C$2:$C$12307,$A12,'Mail List'!$E$2:$E$12307,B$3) -> 200 | C12: =COUNTIFS('Mail List'!$C$2:$C$12307,$A12,'Mail List'!$E$2:$E$12307,C$3) -> 382 | D12: =COUNTIFS('Mail List'!$C$2:$C$12307,$A12,'Mail List'!$E$2:$E$12307,D$3) -> 116 | E12: =COUNTIFS('Mail List'!$C$2:$C$12307,$A12,'Mail List'!$E$2:$E$12307,E$3) -> 368 | F12: =SUM(B12:E12) -> 1066
A13: Palakkad | B13: =COUNTIFS('Mail List'!$C$2:$C$12307,$A13,'Mail List'!$E$2:$E$12307,B$3) -> 65 | C13: =COUNTIFS('Mail List'!$C$2:$C$12307,$A13,'Mail List'!$E$2:$E$12307,C$3) -> 258 | D13: =COUNTIFS('Mail List'!$C$2:$C$12307,$A13,'Mail List'!$E$2:$E$12307,D$3) -> 2 | E13: =COUNTIFS('Mail List'!$C$2:$C$12307,$A13,'Mail List'!$E$2:$E$12307,E$3) -> 384 | F13: =SUM(B13:E13) -> 709
A14: Pathanamthitta | B14: =COUNTIFS('Mail List'!$C$2:$C$12307,$A14,'Mail List'!$E$2:$E$12307,B$3) -> 125 | C14: =COUNTIFS('Mail List'!$C$2:$C$12307,$A14,'Mail List'!$E$2:$E$12307,C$3) -> 174 | D14: =COUNTIFS('Mail List'!$C$2:$C$12307,$A14,'Mail List'!$E$2:$E$12307,D$3) -> 30 | E14: =COUNTIFS('Mail List'!$C$2:$C$12307,$A14,'Mail List'!$E$2:$E$12307,E$3) -> 223 | F14: =SUM(B14:E14) -> 552
A15: Thiruvananthapuram | B15: =COUNTIFS('Mail List'!$C$2:$C$12307,$A15,'Mail List'!$E$2:$E$12307,B$3) -> 333 | C15: =COUNTIFS('Mail List'!$C$2:$C$12307,$A15,'Mail List'!$E$2:$E$12307,C$3) -> 411 | D15: =COUNTIFS('Mail List'!$C$2:$C$12307,$A15,'Mail List'!$E$2:$E$12307,D$3) -> 23 | E15: =COUNTIFS('Mail List'!$C$2:$C$12307,$A15,'Mail List'!$E$2:$E$12307,E$3) -> 479 | F15: =SUM(B15:E15) -> 1246
... A17: Wayanad | B17: =COUNTIFS('Mail List'!$C$2:$C$12307,$A17,'Mail List'!$E$2:$E$12307,B$3) -> 110 | C17: =COUNTIFS('Mail List'!$C$2:$C$12307,$A17,'Mail List'!$E$2:$E$12307,C$3) -> 190 | D17: =COUNTIFS('Mail List'!$C$2:$C$12307,$A17,'Mail List'!$E$2:$E$12307,D$3) -> 2 | E17: =COUNTIFS('Mail List'!$C$2:$C$12307,$A17,'Mail List'!$E$2:$E$12307,E$3) -> 217 | F17: =SUM(B17:E17) -> 519
A18: Total | B18: =SUM(B4:B17) -> 2807 | C18: =SUM(C4:C17) -> 4371 | D18: =SUM(D4:D17) -> 850 | E18: =SUM(E4:E17) -> 4278 | F18: =SUM(F4:F17) -> 12306
A21: Establishments by category
A23: Category | B23: Count
A24: Dental | B24: =COUNTIF('Mail List'!$G$2:$G$12307,$A24) -> 4443
A25: Laboratory | B25: =COUNTIF('Mail List'!$G$2:$G$12307,$A25) -> 4308
A26: Health Centre/Clinics/Polyclinics | B26: =COUNTIF('Mail List'!$G$2:$G$12307,$A26) -> 1304
A27: Both Laboratory and Diagnostic Imaging Centre | B27: =COUNTIF('Mail List'!$G$2:$G$12307,$A27) -> 593
A28: Multi Specialty Hospital | B28: =COUNTIF('Mail List'!$G$2:$G$12307,$A28) -> 585
A29: Single Specialty Hospital | B29: =COUNTIF('Mail List'!$G$2:$G$12307,$A29) -> 542
A30: Day Care Centre | B30: =COUNTIF('Mail List'!$G$2:$G$12307,$A30) -> 214
A31: Any Other | B31: =COUNTIF('Mail List'!$G$2:$G$12307,$A31) -> 138
A32: Diagnostic Imaging Centre | B32: =COUNTIF('Mail List'!$G$2:$G$12307,$A32) -> 118
A33: Teaching Hospital | B33: =COUNTIF('Mail List'!$G$2:$G$12307,$A33) -> 43
A34: Maternity Home | B34: =COUNTIF('Mail List'!$G$2:$G$12307,$A34) -> 11
A35: Dental College | B35: =COUNTIF('Mail List'!$G$2:$G$12307,$A35) -> 6
